{
  "#OTGala5": {
    "duration": 300,
    "tweet_volume": 462991
  },
  "#DAYTONA500": {
    "duration": 195,
    "tweet_volume": 476740
  },
  "#NXTTakeOver": {
    "duration": 450,
    "tweet_volume": 91743
  },
  "Faust\u00e3o": {
    "duration": 165,
    "tweet_volume": 21241
  },
  "#TdelDescuentoFinal": {
    "duration": 255,
    "tweet_volume": 77579
  },
  "#clasicomonumentalxcdf": {
    "duration": 120,
    "tweet_volume": -1
  },
  "\u4e0d\u8981\u4e0d\u6025\u306e\u5916\u51fa": {
    "duration": 390,
    "tweet_volume": 77254
  },
  "Marega": {
    "duration": 195,
    "tweet_volume": 258451
  },
  "Ruth Lorenzo": {
    "duration": 105,
    "tweet_volume": 15343
  },
  "Celta": {
    "duration": 120,
    "tweet_volume": 46145
  },
  "seu jorge": {
    "duration": 15,
    "tweet_volume": -1
  },
  "Bale": {
    "duration": 90,
    "tweet_volume": 33701
  },
  "Rob Manfred": {
    "duration": 135,
    "tweet_volume": 23239
  },
  "Colo Colo": {
    "duration": 30,
    "tweet_volume": 12842
  },
  "Lollo": {
    "duration": 75,
    "tweet_volume": -1
  },
  "Alessandra Negrini": {
    "duration": 150,
    "tweet_volume": 10093
  },
  "Montiel": {
    "duration": 75,
    "tweet_volume": -1
  },
  "Hazard": {
    "duration": 60,
    "tweet_volume": 47249
  },
  "CONTINUE ANNE": {
    "duration": 150,
    "tweet_volume": 53721
  },
  "D  E  W  A  M  K  E": {
    "duration": 90,
    "tweet_volume": -1
  },
  "Blandi": {
    "duration": 60,
    "tweet_volume": -1
  },
  "PJ Walker": {
    "duration": 180,
    "tweet_volume": -1
  },
  "Adam Scott": {
    "duration": 75,
    "tweet_volume": -1
  },
  "AhmetTedaviye AnnesiyleGitsin": {
    "duration": 45,
    "tweet_volume": 198693
  },
  "Dudamel": {
    "duration": 30,
    "tweet_volume": -1
  },
  "Banfield": {
    "duration": 150,
    "tweet_volume": 12134
  },
  "\u30bf\u30c1\u30e3\u30f3\u30ab": {
    "duration": 75,
    "tweet_volume": -1
  },
  "Bernab\u00e9u": {
    "duration": 30,
    "tweet_volume": 18866
  },
  "Jesualdo": {
    "duration": 60,
    "tweet_volume": -1
  },
  "Landry Jones": {
    "duration": 15,
    "tweet_volume": -1
  },
  "Puch": {
    "duration": 15,
    "tweet_volume": -1
  },
  "Yunus Sedat Ayd\u0131n": {
    "duration": 150,
    "tweet_volume": -1
  },
  "#LazioInter": {
    "duration": 165,
    "tweet_volume": 29505
  },
  "#VamosColoColo": {
    "duration": 75,
    "tweet_volume": 10894
  },
  "#LOSCOM": {
    "duration": 90,
    "tweet_volume": 59830
  },
  "#\u0627\u0644\u0644\u064a_\u0628\u062e\u0627\u0637\u0631\u0643\u0645_\u0647\u0627\u062a\u0648\u0647_\u0627\u0644\u0644\u064a\u0644\u0647": {
    "duration": 180,
    "tweet_volume": 24524
  },
  "#COAC2020S1": {
    "duration": 120,
    "tweet_volume": 10727
  },
  "#ReplaceMovieTitleWithTrump": {
    "duration": 330,
    "tweet_volume": 15290
  },
  "#noneladurso": {
    "duration": 105,
    "tweet_volume": 16031
  },
  "#survivor2020": {
    "duration": 90,
    "tweet_volume": 47345
  },
  "#BangwartsReturns": {
    "duration": 270,
    "tweet_volume": 69887
  },
  "#ShadowMan": {
    "duration": 90,
    "tweet_volume": 21966
  },
  "#dingdong": {
    "duration": 30,
    "tweet_volume": 11852
  },
  "#PIT4BUSCH": {
    "duration": 60,
    "tweet_volume": 21122
  },
  "#GONINJAS": {
    "duration": 270,
    "tweet_volume": 20988
  },
  "#\u795e\u69d8\u304c3\u884c\u3067\u8aac\u660e\u3057\u3066\u304f\u308c\u308b\u8a3a\u65ad": {
    "duration": 735,
    "tweet_volume": 20941
  },
  "#\u7aae\u9f20\u306f\u30c1\u30fc\u30ba\u306e\u5922\u3092\u898b\u308b": {
    "duration": 75,
    "tweet_volume": 12852
  },
  "#LGBTQProud": {
    "duration": 60,
    "tweet_volume": 19243
  },
  "#TeamLeBron": {
    "duration": 135,
    "tweet_volume": 63196
  },
  "#CuartoMilenio": {
    "duration": 30,
    "tweet_volume": -1
  },
  "Seu Jorge": {
    "duration": 75,
    "tweet_volume": -1
  },
  "Piero Maza": {
    "duration": 15,
    "tweet_volume": -1
  },
  "Dani Stone": {
    "duration": 90,
    "tweet_volume": -1
  },
  "#AskHHH": {
    "duration": 30,
    "tweet_volume": -1
  },
  "#ATEEZinBrazil": {
    "duration": 150,
    "tweet_volume": 21475
  },
  "Osvaldo": {
    "duration": 210,
    "tweet_volume": 17526
  },
  "NASCAR": {
    "duration": 165,
    "tweet_volume": 260103
  },
  "Coleman": {
    "duration": 195,
    "tweet_volume": 15355
  },
  "Vamos River": {
    "duration": 105,
    "tweet_volume": -1
  },
  "Alexandre Pires": {
    "duration": 15,
    "tweet_volume": -1
  },
  "Munua": {
    "duration": 60,
    "tweet_volume": -1
  },
  "#LosCruzados": {
    "duration": 90,
    "tweet_volume": 11689
  },
  "#\u062a\u0630\u0627\u0643\u0631_\u0627\u0644\u0632\u0645\u0627\u0644\u0643_\u0641\u064a\u0646_\u064a\u0627_\u0627\u0644\u0627\u0645\u0627\u0631\u0627\u062a": {
    "duration": 45,
    "tweet_volume": 61161
  },
  "Javy": {
    "duration": 150,
    "tweet_volume": 61037
  },
  "Roberson": {
    "duration": 30,
    "tweet_volume": -1
  },
  "#askhhh": {
    "duration": 15,
    "tweet_volume": -1
  },
  "Meli": {
    "duration": 120,
    "tweet_volume": 14434
  },
  "Foote": {
    "duration": 15,
    "tweet_volume": -1
  },
  "#NBAAllStarGame": {
    "duration": 285,
    "tweet_volume": 34272
  },
  "#AmericanIdol": {
    "duration": 345,
    "tweet_volume": 22612
  },
  "Jennifer Hudson": {
    "duration": 165,
    "tweet_volume": 49063
  },
  "#OTChat5": {
    "duration": 45,
    "tweet_volume": 27080
  },
  "Salas": {
    "duration": 45,
    "tweet_volume": 16958
  },
  "Nico Domingo": {
    "duration": 45,
    "tweet_volume": -1
  },
  "Sam Roberts": {
    "duration": 15,
    "tweet_volume": -1
  },
  "J Hud": {
    "duration": 15,
    "tweet_volume": -1
  },
  "#NBAAllStar2020": {
    "duration": 165,
    "tweet_volume": 38663
  },
  "#Batwoman": {
    "duration": 165,
    "tweet_volume": -1
  },
  "#BestInRescue": {
    "duration": 150,
    "tweet_volume": -1
  },
  "Common": {
    "duration": 255,
    "tweet_volume": 222866
  },
  "Chaka Khan": {
    "duration": 150,
    "tweet_volume": 33034
  },
  "Fergie": {
    "duration": 270,
    "tweet_volume": 25903
  },
  "Keith Lee": {
    "duration": 30,
    "tweet_volume": -1
  },
  "meli": {
    "duration": 30,
    "tweet_volume": 14327
  },
  "Finn Balor": {
    "duration": 60,
    "tweet_volume": -1
  },
  "Antetokounmpo": {
    "duration": 45,
    "tweet_volume": -1
  },
  "Central C\u00f3rdoba": {
    "duration": 150,
    "tweet_volume": -1
  },
  "Oh Canada": {
    "duration": 75,
    "tweet_volume": -1
  },
  "#FireGarPax": {
    "duration": 390,
    "tweet_volume": 21025
  },
  "#ThingsThatGetBetterWithAge": {
    "duration": 45,
    "tweet_volume": -1
  },
  "National Anthem": {
    "duration": 150,
    "tweet_volume": 63294
  },
  "#laziointer": {
    "duration": 15,
    "tweet_volume": 29218
  },
  "Tevez": {
    "duration": 165,
    "tweet_volume": 17340
  },
  "Monumental": {
    "duration": 30,
    "tweet_volume": 27189
  },
  "Gargano": {
    "duration": 15,
    "tweet_volume": -1
  },
  "#Fantastico": {
    "duration": 120,
    "tweet_volume": -1
  },
  "#90dayfiancetellall": {
    "duration": 15,
    "tweet_volume": -1
  },
  "#ateezinbrazil": {
    "duration": 15,
    "tweet_volume": 18903
  },
  "#OTDirecto17F": {
    "duration": 735,
    "tweet_volume": 100475
  },
  "#IAM48": {
    "duration": 825,
    "tweet_volume": 429280
  },
  "#90DayFiance": {
    "duration": 330,
    "tweet_volume": 16978
  },
  "Team Giannis": {
    "duration": 60,
    "tweet_volume": 26487
  },
  "Soldano": {
    "duration": 135,
    "tweet_volume": -1
  },
  "Manfred": {
    "duration": 30,
    "tweet_volume": 45125
  },
  "#SemifinalLaAcademia": {
    "duration": 450,
    "tweet_volume": 31034
  },
  "#ZoeysPlaylist": {
    "duration": 120,
    "tweet_volume": -1
  },
  "Chris Paul": {
    "duration": 435,
    "tweet_volume": 41593
  },
  "#RHOA": {
    "duration": 330,
    "tweet_volume": 18228
  },
  "Ruso Rodr\u00edguez": {
    "duration": 60,
    "tweet_volume": -1
  },
  "Nahuel": {
    "duration": 360,
    "tweet_volume": 18871
  },
  "All-Star Game": {
    "duration": 105,
    "tweet_volume": 175032
  },
  "#KiaAllStarMVP": {
    "duration": 135,
    "tweet_volume": 23210
  },
  "#NBAAllStarWeekend2020": {
    "duration": 15,
    "tweet_volume": -1
  },
  "#CASAHYYH": {
    "duration": 15,
    "tweet_volume": 15943
  },
  "#Vecinos": {
    "duration": 105,
    "tweet_volume": -1
  },
  "#Supergirl": {
    "duration": 120,
    "tweet_volume": -1
  },
  "Trae Young": {
    "duration": 180,
    "tweet_volume": 25365
  },
  "Rudy Gobert": {
    "duration": 150,
    "tweet_volume": 11922
  },
  "Kyle Lowry": {
    "duration": 435,
    "tweet_volume": 50238
  },
  "#BroserWeights": {
    "duration": 45,
    "tweet_volume": -1
  },
  "#SetorFoto": {
    "duration": 345,
    "tweet_volume": -1
  },
  "#ShahsofSunset": {
    "duration": 30,
    "tweet_volume": -1
  },
  "Chance": {
    "duration": 225,
    "tweet_volume": 513618
  },
  "Ultralight Beam": {
    "duration": 105,
    "tweet_volume": -1
  },
  "Hot Shower": {
    "duration": 90,
    "tweet_volume": -1
  },
  "Flavio": {
    "duration": 90,
    "tweet_volume": 75623
  },
  "DJ Khaled": {
    "duration": 45,
    "tweet_volume": -1
  },
  "Holden": {
    "duration": 495,
    "tweet_volume": 23764
  },
  "#ForaLucas": {
    "duration": 390,
    "tweet_volume": 37048
  },
  "#GoodGirls": {
    "duration": 240,
    "tweet_volume": 10767
  },
  "Adam Cole": {
    "duration": 60,
    "tweet_volume": -1
  },
  "javy": {
    "duration": 15,
    "tweet_volume": 60975
  },
  "#\u3042\u306a\u305f\u306e\u5fc3\u306e\u6c5a\u67d3\u5ea6\u306f": {
    "duration": 285,
    "tweet_volume": -1
  },
  "#BodhDiwas_SaintRampalJi": {
    "duration": 420,
    "tweet_volume": 547283
  },
  "#mondaythoughts": {
    "duration": 345,
    "tweet_volume": 20326
  },
  "#broserweights": {
    "duration": 15,
    "tweet_volume": -1
  },
  "#LastWordsOnTheTitanic": {
    "duration": 30,
    "tweet_volume": -1
  },
  "#ForaVictorHugo": {
    "duration": 60,
    "tweet_volume": -1
  },
  "#GiannisAntetokounmpo": {
    "duration": 15,
    "tweet_volume": -1
  },
  "#NBAAllStar": {
    "duration": 90,
    "tweet_volume": 261530
  },
  "Ciampa": {
    "duration": 105,
    "tweet_volume": 11167
  },
  "Nick Nurse": {
    "duration": 180,
    "tweet_volume": -1
  },
  "#\u00c7okG\u00fczelsin\u00d6zgeYa\u011f\u0131z": {
    "duration": 285,
    "tweet_volume": -1
  },
  "#WonhoIsMySomeone": {
    "duration": 30,
    "tweet_volume": -1
  },
  "#fantastico": {
    "duration": 15,
    "tweet_volume": -1
  },
  "#sisterwives": {
    "duration": 15,
    "tweet_volume": -1
  },
  "Giannis": {
    "duration": 270,
    "tweet_volume": 122917
  },
  "James Harden": {
    "duration": 120,
    "tweet_volume": 12989
  },
  "Kemba Walker": {
    "duration": 30,
    "tweet_volume": -1
  },
  "Elam Ending": {
    "duration": 90,
    "tweet_volume": -1
  },
  "Reggie Miller": {
    "duration": 90,
    "tweet_volume": -1
  },
  "#SKZUNLOCKinLA": {
    "duration": 285,
    "tweet_volume": 63517
  },
  "Anthony Davis": {
    "duration": 90,
    "tweet_volume": 19312
  },
  "Best All-Star": {
    "duration": 30,
    "tweet_volume": 17222
  },
  "Win by 2": {
    "duration": 120,
    "tweet_volume": -1
  },
  "Adam Silver": {
    "duration": 45,
    "tweet_volume": 19914
  },
  "tevez": {
    "duration": 15,
    "tweet_volume": 17108
  },
  "Kawhi MVP": {
    "duration": 15,
    "tweet_volume": -1
  },
  "#askgigi": {
    "duration": 195,
    "tweet_volume": -1
  },
  "#foravictorhugo": {
    "duration": 15,
    "tweet_volume": -1
  },
  "#SevenIsTheHappiestNumber": {
    "duration": 330,
    "tweet_volume": 20414
  },
  "Kawhi": {
    "duration": 255,
    "tweet_volume": 139447
  },
  "Kemba": {
    "duration": 165,
    "tweet_volume": 21545
  },
  "Best ASG": {
    "duration": 15,
    "tweet_volume": -1
  },
  "Kobe Bryant MVP": {
    "duration": 75,
    "tweet_volume": 26385
  },
  "#americanidol": {
    "duration": 15,
    "tweet_volume": 20492
  },
  "#HablandoConMarioB": {
    "duration": 135,
    "tweet_volume": -1
  },
  "#\u0645\u0648\u0633\u0645_\u0639\u0633\u0644_\u0648\u0639\u0627\u0641\u064a\u0647": {
    "duration": 45,
    "tweet_volume": -1
  },
  "#\u0646\u0627\u064a\u0641_\u062d\u0645\u062f\u0627\u0646": {
    "duration": 375,
    "tweet_volume": 15514
  },
  "#\u56fd\u4f1a\u4e2d\u7d99": {
    "duration": 270,
    "tweet_volume": 33198
  },
  "#ParalarNerede": {
    "duration": 180,
    "tweet_volume": -1
  },
  "The NBA": {
    "duration": 15,
    "tweet_volume": 129355
  },
  "best asg": {
    "duration": 15,
    "tweet_volume": -1
  },
  "Beilein": {
    "duration": 15,
    "tweet_volume": -1
  },
  "#JusticiaParaFatima": {
    "duration": 705,
    "tweet_volume": 210598
  },
  "#HerkeseBendenAtama": {
    "duration": 60,
    "tweet_volume": -1
  },
  "O Lucas": {
    "duration": 60,
    "tweet_volume": 113156
  },
  "\u5929\u7687\u8a95\u751f\u65e5\u306e\u4e00\u822c\u53c2\u8cc0": {
    "duration": 150,
    "tweet_volume": 14128
  },
  "#DoctorFirstLook": {
    "duration": 195,
    "tweet_volume": 33986
  },
  "#Tejas": {
    "duration": 105,
    "tweet_volume": -1
  },
  "#ABDevilliers": {
    "duration": 150,
    "tweet_volume": 10842
  },
  "#pazartesi": {
    "duration": 375,
    "tweet_volume": 32933
  },
  "#OmbudsmanApresiasiPolri": {
    "duration": 165,
    "tweet_volume": 139069
  },
  "Harden": {
    "duration": 150,
    "tweet_volume": 56605
  },
  "#FelizLunes": {
    "duration": 765,
    "tweet_volume": 47135
  },
  "win by 2": {
    "duration": 15,
    "tweet_volume": -1
  },
  "\u4e00\u822c\u53c2\u52a0\u4e2d\u6b62": {
    "duration": 15,
    "tweet_volume": -1
  },
  "#GoldenChildCopyChoreography": {
    "duration": 315,
    "tweet_volume": 45209
  },
  "#paralarnerede": {
    "duration": 15,
    "tweet_volume": -1
  },
  "#PesanUntukMantan": {
    "duration": 585,
    "tweet_volume": 13297
  },
  "#hacettepe": {
    "duration": 375,
    "tweet_volume": -1
  },
  "#RingkusAlfianTanjung": {
    "duration": 255,
    "tweet_volume": 15246
  },
  "#\u0633\u0641\u064a\u0647_\u0627\u0644\u062f\u0648\u062d\u0647_\u0648\u062c\u0632\u064a\u0647_\u0627\u0644\u0645\u0631\u062a\u0632\u0642\u0647": {
    "duration": 75,
    "tweet_volume": 11485
  },
  "#BincangSeruMahfud": {
    "duration": 135,
    "tweet_volume": -1
  },
  "#justiciaparaf\u00e1tima": {
    "duration": 105,
    "tweet_volume": 23203
  },
  "Harry Gregg": {
    "duration": 315,
    "tweet_volume": 22265
  },
  "#\u0645\u0646\u062c\u0632_\u062a\u0642\u0646\u064a": {
    "duration": 120,
    "tweet_volume": -1
  },
  "#\u4fe1\u8005\u3068\u30d5\u30a1\u30f3\u3068\u30a2\u30f3\u30c1": {
    "duration": 540,
    "tweet_volume": 26112
  },
  "#nbaallstargame": {
    "duration": 15,
    "tweet_volume": 32674
  },
  "#kiaallstarmvp": {
    "duration": 15,
    "tweet_volume": 23328
  },
  "#THETRAD": {
    "duration": 60,
    "tweet_volume": -1
  },
  "#\u0645\u0647\u0631\u062c\u0627\u0627\u0627\u0646_\u0627\u0644\u0642\u0631\u0627\u0621\u0647_\u0627\u0644\u062d\u0631\u0647": {
    "duration": 135,
    "tweet_volume": -1
  },
  "#17febbraio": {
    "duration": 270,
    "tweet_volume": -1
  },
  "#\uc138\uc0c1\uc5d0\ubbfc\ud601\uc774\ub294\ub9ce\uace0\ub10c\uc798\uc0dd\uacbc\ub2e8\ub2e4": {
    "duration": 120,
    "tweet_volume": -1
  },
  "\u304a\u524d\u306e\u305b\u3044": {
    "duration": 435,
    "tweet_volume": 142800
  },
  "#NXTakeOver": {
    "duration": 30,
    "tweet_volume": 14456
  },
  "#MondayMotivaton": {
    "duration": 135,
    "tweet_volume": 21334
  },
  "#\u0635\u062f\u0642\u064a\u0646\u064a_\u064a\u0627\u0645\u0647\u0627_\u0627\u062d\u0628\u0643": {
    "duration": 450,
    "tweet_volume": 11084
  },
  "#\u0627\u0644\u0627\u0633\u064a\u0648\u064a\u0647_\u0635\u0639\u0628\u0647_\u0642\u0648\u064a\u0647_\u064a\u0627\u0646\u0635\u0631": {
    "duration": 135,
    "tweet_volume": -1
  },
  "#FiestaWithIZONE": {
    "duration": 480,
    "tweet_volume": 265305
  },
  "#\u062c\u062f\u0647_\u0627\u0644\u0627\u0646": {
    "duration": 165,
    "tweet_volume": 15168
  },
  "#thetrad": {
    "duration": 30,
    "tweet_volume": -1
  },
  "#\u0633\u062f\u0627\u062f_\u0642\u0631\u0648\u0636\u0643_\u0627\u0644\u0628\u0646\u0643\u064a": {
    "duration": 60,
    "tweet_volume": -1
  },
  "#\u3086\u3046\u304c\u305f\u30d1\u30e9\u30c0\u30a4\u30b9": {
    "duration": 150,
    "tweet_volume": -1
  },
  "#PIXIVTECHFES": {
    "duration": 225,
    "tweet_volume": -1
  },
  "#BourdinDirect": {
    "duration": 30,
    "tweet_volume": -1
  },
  "#\u0e2d\u0e30\u0e2d\u0e37\u0e49\u0e2d": {
    "duration": 105,
    "tweet_volume": 25105
  },
  "#UnderRutoIn23Mins": {
    "duration": 255,
    "tweet_volume": -1
  },
  "#RandomActsOfKindnessDay": {
    "duration": 630,
    "tweet_volume": 38473
  },
  "\u5317\u4eac\u516c\u6f14\u4e2d\u6b62": {
    "duration": 180,
    "tweet_volume": 16387
  },
  "\u30cf\u30a4\u30e2\u30c7\u30eb\u5316": {
    "duration": 150,
    "tweet_volume": -1
  },
  "\u5317\u4eac\u4e2d\u6b62": {
    "duration": 90,
    "tweet_volume": 14663
  },
  "\u30b8\u30e3\u30cb\u30fc\u30ba\u4e8b\u52d9\u6240\u516c\u5f0f\u30b5\u30a4\u30c8": {
    "duration": 45,
    "tweet_volume": -1
  },
  "#JusticiaParaF\u00e1tima": {
    "duration": 90,
    "tweet_volume": 23482
  },
  "#AllStarNBA": {
    "duration": 15,
    "tweet_volume": -1
  },
  "#AskAMan": {
    "duration": 105,
    "tweet_volume": -1
  },
  "Ali \u015een": {
    "duration": 135,
    "tweet_volume": -1
  },
  "Johnny's net": {
    "duration": 15,
    "tweet_volume": -1
  },
  "#\u0627\u062d\u0641\u0638_\u0648\u0635\u0627\u062a\u064a_\u0648\u0627\u0644\u0648\u0635\u0627\u0647_\u0627\u0639\u062a\u0645\u062f\u0647\u0627": {
    "duration": 75,
    "tweet_volume": -1
  },
  "#\u0647\u0646\u0627_\u062a\u0645\u0648\u064a\u0644\u0643_\u0627\u0644\u0639\u0642\u0627\u0631\u064a": {
    "duration": 15,
    "tweet_volume": -1
  },
  "#iyikido\u011fdunkadir": {
    "duration": 165,
    "tweet_volume": -1
  },
  "#puhon": {
    "duration": 585,
    "tweet_volume": 11071
  },
  "#\u0627\u0644\u0627\u062c\u0648\u0627\u0621_\u0627\u0644\u062d\u0644\u0648\u0647": {
    "duration": 120,
    "tweet_volume": -1
  },
  "#D\u00fcnyaKedilerG\u00fcn\u00fc": {
    "duration": 795,
    "tweet_volume": 23538
  },
  "#\u0627\u0644\u0647\u0644\u0627\u0644_\u0634\u0628\u0627\u0628_\u0627\u0644\u0627\u0647\u0644\u064a": {
    "duration": 645,
    "tweet_volume": 133988
  },
  "#mecagoendios": {
    "duration": 315,
    "tweet_volume": -1
  },
  "\ud53c\uc5d0\uc2a4\ud0c0": {
    "duration": 255,
    "tweet_volume": 251338
  },
  "\u30e9\u30c3\u30b7\u30e5\u30c7\u30e5\u30a8\u30eb": {
    "duration": 105,
    "tweet_volume": -1
  },
  "#CHEMUN": {
    "duration": 780,
    "tweet_volume": 220521
  },
  "#stormdennisuk": {
    "duration": 105,
    "tweet_volume": -1
  },
  "#DKP": {
    "duration": 75,
    "tweet_volume": -1
  },
  "IZ*ONE": {
    "duration": 105,
    "tweet_volume": 222823
  },
  "#\u0647\u0632\u0647_\u0627\u0631\u0636\u064a\u0647_\u0627\u0644\u0645\u062f\u064a\u0646\u0647": {
    "duration": 255,
    "tweet_volume": 23674
  },
  "#RipuhPerdaKTRBogor": {
    "duration": 75,
    "tweet_volume": -1
  },
  "#semifinallaacademia": {
    "duration": 15,
    "tweet_volume": 31046
  },
  "Mustafa Kap\u0131": {
    "duration": 270,
    "tweet_volume": -1
  },
  "\u30b8\u30e3\u30cb\u30fc\u30baweb": {
    "duration": 135,
    "tweet_volume": -1
  },
  "#4corners": {
    "duration": 150,
    "tweet_volume": -1
  },
  "#BuenLunes": {
    "duration": 30,
    "tweet_volume": -1
  },
  "#festadelgatto": {
    "duration": 75,
    "tweet_volume": -1
  },
  "#StKevins": {
    "duration": 30,
    "tweet_volume": -1
  },
  "Lowry": {
    "duration": 15,
    "tweet_volume": 81833
  },
  "Willy Toledo": {
    "duration": 105,
    "tweet_volume": 46482
  },
  "\ub300\uc778\uae30\ud53c\uc99d": {
    "duration": 15,
    "tweet_volume": -1
  },
  "#PlayerOftheYear": {
    "duration": 75,
    "tweet_volume": -1
  },
  "#\u062a\u0637\u0628\u064a\u0642_\u0627\u0633\u0631_\u0627\u0644\u062e\u064a\u0631_\u064a\u062f\u0639\u0645_\u0627\u0644\u0627\u0633\u0631": {
    "duration": 105,
    "tweet_volume": -1
  },
  "#Amthor": {
    "duration": 15,
    "tweet_volume": -1
  },
  "#\u3050\u3093\u304b\u3093\u30aa\u30d5\u30b3\u30e9\u30dc": {
    "duration": 15,
    "tweet_volume": -1
  },
  "5 GrabFood": {
    "duration": 270,
    "tweet_volume": -1
  },
  "\u540d\u53e4\u5c4b\u306e\u96e3\u8aad\u5730\u540d\u30af\u30a4\u30ba": {
    "duration": 240,
    "tweet_volume": -1
  },
  "\u53c2\u52a0\u6599": {
    "duration": 195,
    "tweet_volume": 17721
  },
  "#\u062d\u0627\u0636\u0631\u064a\u0646": {
    "duration": 165,
    "tweet_volume": -1
  },
  "#Yalanc\u0131B\u00f6cek": {
    "duration": 120,
    "tweet_volume": -1
  },
  "#T\u00edraUnTripleNBA2k": {
    "duration": 90,
    "tweet_volume": -1
  },
  "willy toledo": {
    "duration": 15,
    "tweet_volume": 25158
  },
  "#MondayMorning": {
    "duration": 45,
    "tweet_volume": 13051
  },
  "#PamilyaKoSayongMundo": {
    "duration": 30,
    "tweet_volume": 13862
  },
  "#\u540d\u53e4\u5c4b\u96e3\u8aad\u5730\u540d": {
    "duration": 30,
    "tweet_volume": -1
  },
  "#EstudiarHumanidadesEs": {
    "duration": 285,
    "tweet_volume": -1
  },
  "#qanda": {
    "duration": 210,
    "tweet_volume": 11221
  },
  "#\u30b7\u30e3\u30cb\u30de\u30b9\u751f\u914d\u4fe1": {
    "duration": 255,
    "tweet_volume": 22500
  },
  "\uc548\ubb34\uc601\uc0c1": {
    "duration": 120,
    "tweet_volume": 19817
  },
  "#karataymedresesi": {
    "duration": 150,
    "tweet_volume": -1
  },
  "#Yuehua_believein_us": {
    "duration": 330,
    "tweet_volume": 521963
  },
  "#\u0645\u0647\u0631\u062c\u0627\u0646_\u0627\u0644\u0634\u0631\u0642\u064a\u0647_\u0644\u0644\u062e\u064a\u0644_\u0627\u0644\u0639\u0631\u0628\u064a\u0647": {
    "duration": 120,
    "tweet_volume": -1
  },
  "5 Red Velvet": {
    "duration": 15,
    "tweet_volume": -1
  },
  "#FiestaXboxGamePass": {
    "duration": 285,
    "tweet_volume": -1
  },
  "#\u30db\u30ed\u5927\u5bcc\u8c6a": {
    "duration": 105,
    "tweet_volume": -1
  },
  "#D7TilSB19inIMUS": {
    "duration": 15,
    "tweet_volume": 71937
  },
  "\uc544\uc774\uc988": {
    "duration": 105,
    "tweet_volume": 196455
  },
  "#Q\u3055\u307e": {
    "duration": 240,
    "tweet_volume": 23084
  },
  "#WannaOne": {
    "duration": 240,
    "tweet_volume": 69472
  },
  "#\u0639\u0632\u0648\u0632_\u062b\u0627\u0645\u0631_\u0645\u0628\u0631\u0648\u0643_\u0627\u0644\u062a\u0648\u062b\u064a\u0642": {
    "duration": 30,
    "tweet_volume": -1
  },
  "#PlayerOfTheYear": {
    "duration": 60,
    "tweet_volume": -1
  },
  "#\u4e16\u754c\u307e\u308b\u898b\u3048": {
    "duration": 45,
    "tweet_volume": -1
  },
  "\u30a4\u30f3\u30bf\u30fc\u30cd\u30c3\u30c8": {
    "duration": 90,
    "tweet_volume": 117717
  },
  "5 grabfood": {
    "duration": 15,
    "tweet_volume": -1
  },
  "\ub300\uae30\ubc88\ud638": {
    "duration": 45,
    "tweet_volume": -1
  },
  "#\u30b9\u30ab\u30c3\u3068\u30b8\u30e3\u30d1\u30f3": {
    "duration": 150,
    "tweet_volume": 10190
  },
  "#VTeaser": {
    "duration": 120,
    "tweet_volume": 19103
  },
  "#Nirbhaya": {
    "duration": 30,
    "tweet_volume": -1
  },
  "#17Feb": {
    "duration": 495,
    "tweet_volume": 62056
  },
  "#\u3084\u3057\u304d\u305a3D": {
    "duration": 300,
    "tweet_volume": 39528
  },
  "#\u30c7\u30ec\u30e9\u30b8": {
    "duration": 135,
    "tweet_volume": -1
  },
  "#\u30a2\u30ad\u30ed\u30bc\u751f\u8a95\u796d": {
    "duration": 180,
    "tweet_volume": -1
  },
  "#MondayMood": {
    "duration": 45,
    "tweet_volume": 21330
  },
  "#PresidentsDay": {
    "duration": 315,
    "tweet_volume": 141379
  },
  "CHUDOKU": {
    "duration": 195,
    "tweet_volume": 15763
  },
  "IKKO\u3055\u3093": {
    "duration": 120,
    "tweet_volume": 11946
  },
  "\u3053\u3046\u3061\u3083\u3093": {
    "duration": 75,
    "tweet_volume": 21498
  },
  "#MondayMotivation": {
    "duration": 240,
    "tweet_volume": 79655
  },
  "#\u7d76\u5bfe\u96f6\u5ea6": {
    "duration": 135,
    "tweet_volume": -1
  },
  "#playeroftheyear": {
    "duration": 15,
    "tweet_volume": -1
  },
  "\u97f3\u30b2\u30fc\u30de\u30fc\u306e\u624b\u634c\u304d": {
    "duration": 30,
    "tweet_volume": -1
  },
  "#QuizKnock": {
    "duration": 45,
    "tweet_volume": 10683
  },
  "#\u30d2\u30d7\u30e9\u30b8": {
    "duration": 90,
    "tweet_volume": 10574
  },
  "PEACH\u306e\u8863\u88c5": {
    "duration": 90,
    "tweet_volume": -1
  },
  "#wannaone": {
    "duration": 15,
    "tweet_volume": 39491
  },
  "#FelizInicioDeSemana": {
    "duration": 15,
    "tweet_volume": -1
  },
  "#\uc81c\uc774\ud649_\ub108\ud558\ub098\ub85c_\ub2e4_\uc704\ub85c\uac00_\ub41c\ub2e4\ub294\uac78": {
    "duration": 420,
    "tweet_volume": 523293
  },
  "#bartomeuout": {
    "duration": 105,
    "tweet_volume": -1
  },
  "#\u5fa9\u8208\u306b\u5411\u3051\u3066\u624b\u3092\u7e4b\u3054\u3046": {
    "duration": 120,
    "tweet_volume": 25028
  },
  "#MIWYHighInLove": {
    "duration": 105,
    "tweet_volume": 96434
  },
  "#\u3057\u3083\u3079\u304f\u308a007": {
    "duration": 135,
    "tweet_volume": -1
  },
  "ikko\u3055\u3093": {
    "duration": 15,
    "tweet_volume": -1
  },
  "#PresidentsDay2020": {
    "duration": 285,
    "tweet_volume": 68886
  },
  "#IZONE_FIESTA": {
    "duration": 15,
    "tweet_volume": 213153
  },
  "#\u0645\u0647\u0631\u062c\u0627\u0646_\u062c\u062f\u0647_\u0644\u0644\u062c\u0645\u064a\u0639": {
    "duration": 75,
    "tweet_volume": -1
  },
  "#\u0e2d\u0e34\u0e19\u0e1f\u0e34\u0e19\u0e34\u0e17\u0e27\u0e07\u0e44\u0e23": {
    "duration": 300,
    "tweet_volume": 70165
  },
  "#AyalaanFirstLook": {
    "duration": 105,
    "tweet_volume": 38242
  },
  "#\u5e73\u624b\u53cb\u68a8\u5948": {
    "duration": 90,
    "tweet_volume": -1
  },
  "#JhopeBirthday": {
    "duration": 45,
    "tweet_volume": 25067
  },
  "#\u897f\u904a\u8a18": {
    "duration": 75,
    "tweet_volume": -1
  },
  "#fiestaxboxgamepass": {
    "duration": 15,
    "tweet_volume": -1
  },
  "#\u30b9\u30de\u30b9\u30de": {
    "duration": 15,
    "tweet_volume": 22170
  },
  "#GoingSeventeen": {
    "duration": 75,
    "tweet_volume": -1
  },
  "#BotafogoComYaya": {
    "duration": 525,
    "tweet_volume": 54975
  },
  "#\u0633\u0646\u0627\u0628_\u0639\u0645\u0631_\u0627\u0644\u0645\u0636\u062d\u064a_o_almodhhi": {
    "duration": 15,
    "tweet_volume": -1
  },
  "Andrew Weatherall": {
    "duration": 360,
    "tweet_volume": 22386
  },
  "\ub4dc\ub77c\ud058\ub77c": {
    "duration": 60,
    "tweet_volume": 15600
  },
  "#BartomeuOUT": {
    "duration": 540,
    "tweet_volume": 81418
  },
  "#TREASUREBABYJUNGHWANDAY": {
    "duration": 270,
    "tweet_volume": 41736
  },
  "#\ub3c4\uacb8_\ubc84\ub17c_218\ube0c\ub85c_\uc0dd\uc77c\ucd95\ud558\ud574": {
    "duration": 315,
    "tweet_volume": 135530
  },
  "#\u0633\u0646\u0627\u0628_\u0631\u0641\u0627\u0647_\u0627\u0644\u0631\u064a\u0627\u0636": {
    "duration": 15,
    "tweet_volume": -1
  },
  "#HappyBirthdayJhope": {
    "duration": 480,
    "tweet_volume": 1326807
  },
  "#\u0645\u0647\u0631\u062c\u0627\u0627\u0627\u0646_\u062c\u062f\u0647_\u0644\u0644\u062c\u0645\u064a\u0639": {
    "duration": 75,
    "tweet_volume": -1
  },
  "#pesanuntukmantan": {
    "duration": 15,
    "tweet_volume": 11341
  },
  "#DeerMyMaxDay": {
    "duration": 225,
    "tweet_volume": 51802
  },
  "#\u307a\u3053\u307f\u3053\u3053\u590f": {
    "duration": 45,
    "tweet_volume": -1
  },
  "#FamilyDay": {
    "duration": 195,
    "tweet_volume": 10175
  },
  "#\u30a2\u30c3\u30d1\u30ec173": {
    "duration": 15,
    "tweet_volume": -1
  },
  "#\ud558\ub098\ubfd0\uc778_Jhope_\ud558\ub098\ubfd0\uc778_\ub108": {
    "duration": 15,
    "tweet_volume": 100707
  },
  "#\u4f0a\u91ce\u5c3e\u304f\u3093\u306e\u898b\u305f\u76ee\u4ee5\u4e0a": {
    "duration": 195,
    "tweet_volume": 11731
  },
  "#NeoZoneChartShow": {
    "duration": 510,
    "tweet_volume": 191224
  },
  "#familyday2020": {
    "duration": 15,
    "tweet_volume": -1
  },
  "#\ud638\ube44\uc0dd\uc77c\u110e\u110f": {
    "duration": 15,
    "tweet_volume": 233458
  },
  "#\uc81c\uc774\ud649_\ub110_\ub9cc\ub09c\uac74_\ud589\uc6b4\uc774\uc790_\ud589\ubcf5": {
    "duration": 30,
    "tweet_volume": 14639
  },
  "#reco1134": {
    "duration": 75,
    "tweet_volume": 14028
  },
  "#\u4ed9\u53f0\u5f01\u4f1a\u8a71\u30af\u30a4\u30ba": {
    "duration": 15,
    "tweet_volume": -1
  },
  "#\u0647\u062f\u064a\u062a\u0643_\u0627\u064a\u0641\u0648\u0646_\u0645\u0646_\u0648\u0627\u0648\u0641\u0648\u0646": {
    "duration": 15,
    "tweet_volume": -1
  },
  "#A\u3047group\u7d50\u62101\u5468\u5e74": {
    "duration": 225,
    "tweet_volume": 15001
  },
  "#15BDTurns2": {
    "duration": 15,
    "tweet_volume": -1
  },
  "\uc815\ud638\uc11d": {
    "duration": 30,
    "tweet_volume": 81116
  },
  "#\ud638\ube44\ub294_\uc544\ubbf8\uc758_\ud76c\ub9dd": {
    "duration": 45,
    "tweet_volume": 16550
  },
  "#Happy_DK_Day": {
    "duration": 60,
    "tweet_volume": 39746
  },
  "#\ud638\uc11d\uc544_\ub10c_\uc6b0\ub9ac\uc758_\uc601\uc6d0\ud55c_\ud76c\ub9dd": {
    "duration": 30,
    "tweet_volume": 33378
  },
  "#doya": {
    "duration": 60,
    "tweet_volume": -1
  },
  "#\uc6b4\uba85\uc774\ub410\uace0\uc911\uc2ec\uc774\ub410\uc5b4": {
    "duration": 60,
    "tweet_volume": 288237
  },
  "#felizlunes": {
    "duration": 15,
    "tweet_volume": 33993
  },
  "#\u0627\u0644\u0639\u0631\u0636\u0647_\u0628\u0645\u0647\u0631\u062c\u0627\u0646_\u062c\u062f\u0647_\u0644\u0644\u062c\u0645\u064a\u0639": {
    "duration": 120,
    "tweet_volume": -1
  },
  "#FRPOynuyoruz": {
    "duration": 30,
    "tweet_volume": -1
  },
  "#200KOFMEW": {
    "duration": 120,
    "tweet_volume": 71354
  },
  "#BTSCarpoolFEB25": {
    "duration": 225,
    "tweet_volume": 148245
  },
  "#hobi_brightens_our_world": {
    "duration": 120,
    "tweet_volume": -1
  },
  "#\u0645\u0648\u0646\u062f\u064a\u0627\u06442020_\u064a\u062d\u0635\u062f_\u0627\u0644\u0627\u0631\u0648\u0627\u062d": {
    "duration": 15,
    "tweet_volume": -1
  },
  "#\u6708\u66dc\u304b\u3089\u591c\u3075\u304b\u3057": {
    "duration": 105,
    "tweet_volume": -1
  },
  "Jung Hoseok": {
    "duration": 30,
    "tweet_volume": 106014
  },
  "#\ub098\uc758_\ud76c\ub9dd\uc740_\ud638\uc11d\uc774_\ud589\ubcf5": {
    "duration": 105,
    "tweet_volume": 59504
  },
  "#\u0627\u0627\u0627\u0644\u0639\u0631\u0636\u0647_\u0628\u0645\u0647\u0631\u062c\u0627\u0646_\u062c\u062f\u0647_\u0644\u0644\u062c\u0645\u064a\u0639": {
    "duration": 75,
    "tweet_volume": -1
  },
  "#\u0645\u0648\u0646\u062f\u064a\u0627\u06442022_\u064a\u062d\u0635\u062f_\u0627\u0644\u0627\u0631\u0648\u0627\u062d": {
    "duration": 180,
    "tweet_volume": -1
  },
  "#randomactsofkindnessday": {
    "duration": 15,
    "tweet_volume": 25603
  },
  "#\u0e01\u0e49\u0e2d\u0e15\u0e40\u0e2a\u0e40\u0e27\u0e48\u0e19\u0e27\u0e07\u0e2d\u0e30\u0e44\u0e23": {
    "duration": 150,
    "tweet_volume": 62701
  },
  "#MersindeB\u00fcy\u00fckDoland\u0131r\u0131c\u0131": {
    "duration": 75,
    "tweet_volume": -1
  },
  "#HopeAlwaysHere": {
    "duration": 75,
    "tweet_volume": 426929
  },
  "#\uc774\uc820_\uc6b0\ub9ac\uac00_\ud638\uc11d\uc758_\ud76c\ub9dd\uc774_\ub418\uc5b4\uc904\uac8c": {
    "duration": 45,
    "tweet_volume": 242890
  },
  "#CumhurReistenEk40Bin\u00d6\u011frt": {
    "duration": 225,
    "tweet_volume": 102380
  },
  "#HobiDay": {
    "duration": 15,
    "tweet_volume": 48138
  },
  "J-Hope": {
    "duration": 30,
    "tweet_volume": 267370
  },
  "#RTXOn": {
    "duration": 405,
    "tweet_volume": 199862
  },
  "#\uc18c\uc911\ud55c_\uc18c\uc815\ud658_\ube5b\ubd04": {
    "duration": 45,
    "tweet_volume": 28923
  },
  "#Rehbltsyn\u00d6\u011frtMeslekKanunu": {
    "duration": 195,
    "tweet_volume": 17629
  },
  "#mersindeb\u00fcy\u00fckdoland\u0131r\u0131c\u0131": {
    "duration": 15,
    "tweet_volume": -1
  },
  "#SomosPatriaInexpugnable": {
    "duration": 60,
    "tweet_volume": 52102
  },
  "#HOBIUARY": {
    "duration": 15,
    "tweet_volume": 30073
  },
  "#Happy_Vernon_Day": {
    "duration": 15,
    "tweet_volume": 45947
  },
  "#yanda\u015fape\u015fke\u015f": {
    "duration": 60,
    "tweet_volume": -1
  },
  "#YavuzH\u0131rs\u0131zT\u00fcrel": {
    "duration": 165,
    "tweet_volume": -1
  },
  "#Ormandam\u00fclakatiptal": {
    "duration": 165,
    "tweet_volume": -1
  },
  "#ConfesionDeAida": {
    "duration": 345,
    "tweet_volume": 41508
  },
  "#kimleroradayd\u0131": {
    "duration": 30,
    "tweet_volume": -1
  },
  "Esnafa\u00c7ile \u00c7ekTirmeyin": {
    "duration": 135,
    "tweet_volume": 49680
  },
  "#Yan\u0131ndaOlaca\u011f\u0131m": {
    "duration": 330,
    "tweet_volume": 80468
  },
  "#\u0627\u0644\u0627\u0647\u0644\u064a_\u0627\u0644\u0633\u0639\u0648\u062f\u064a_\u0627\u0644\u0627\u0633\u062a\u0642\u0644\u0627\u0644": {
    "duration": 75,
    "tweet_volume": 38354
  },
  "#LovelyHopeChallenge": {
    "duration": 45,
    "tweet_volume": 124411
  },
  "#BreakFreePersona": {
    "duration": 345,
    "tweet_volume": 15748
  },
  "#IndonesianIdol": {
    "duration": 45,
    "tweet_volume": -1
  },
  "#MakeAMovieFancy": {
    "duration": 105,
    "tweet_volume": -1
  },
  "#OurPrettyHobi": {
    "duration": 15,
    "tweet_volume": 272510
  },
  "B\u00fc\u015fraHamile AcilenTahliye": {
    "duration": 285,
    "tweet_volume": 83675
  },
  "Richard Linares": {
    "duration": 75,
    "tweet_volume": 23763
  },
  "#HOSEOKDAY": {
    "duration": 165,
    "tweet_volume": 52922
  },
  "#HappyHoseokDay": {
    "duration": 15,
    "tweet_volume": 53331
  },
  "#BabamaS\u00f6zVerdim": {
    "duration": 285,
    "tweet_volume": 33262
  },
  "#\u0648\u064a\u0646\u0647_\u0630\u0627\u0643_\u0627\u0644\u062d\u0646\u0627\u0646": {
    "duration": 45,
    "tweet_volume": -1
  },
  "American Deli": {
    "duration": 60,
    "tweet_volume": -1
  },
  "Mike Tomlin": {
    "duration": 15,
    "tweet_volume": -1
  },
  "Girauta": {
    "duration": 60,
    "tweet_volume": -1
  },
  "#\u0627\u0645\u0631_\u0627\u062e\u0644\u0627\u0621": {
    "duration": 165,
    "tweet_volume": 16995
  },
  "#SivaSSuskunlu\u011funuBozuyor": {
    "duration": 150,
    "tweet_volume": 14739
  },
  "#destekolunmeslekolal\u0131m": {
    "duration": 75,
    "tweet_volume": 34021
  },
  "#QuettaBlast": {
    "duration": 60,
    "tweet_volume": 13422
  },
  "Bailly": {
    "duration": 285,
    "tweet_volume": 48013
  },
  "Mike Trout": {
    "duration": 60,
    "tweet_volume": 15605
  },
  "Vernaci": {
    "duration": 120,
    "tweet_volume": 11709
  },
  "#Olmasasdim": {
    "duration": 120,
    "tweet_volume": -1
  },
  "#DK_VERNON_218bro_DAY": {
    "duration": 60,
    "tweet_volume": 73864
  },
  "#AskMonstaX": {
    "duration": 300,
    "tweet_volume": 15385
  },
  "#cizre": {
    "duration": 285,
    "tweet_volume": -1
  },
  "#Laureus20": {
    "duration": 120,
    "tweet_volume": 19947
  },
  "#RandomActsofColourpop": {
    "duration": 240,
    "tweet_volume": -1
  },
  "#\u0627\u0644\u062d\u0628_\u0628\u0627\u062e\u062a\u0635\u0627\u0631": {
    "duration": 285,
    "tweet_volume": 20286
  },
  "#LMAC": {
    "duration": 75,
    "tweet_volume": -1
  },
  "Batshuayi": {
    "duration": 210,
    "tweet_volume": 31317
  },
  "Soparia da Socorro": {
    "duration": 15,
    "tweet_volume": -1
  },
  "#SamsunluK\u0131zlar\u00c7okG\u00fczeldir": {
    "duration": 135,
    "tweet_volume": -1
  },
  "Roy Keane": {
    "duration": 180,
    "tweet_volume": -1
  },
  "The Varsity": {
    "duration": 15,
    "tweet_volume": -1
  },
  "#Konyaalt\u0131sahili": {
    "duration": 75,
    "tweet_volume": -1
  },
  "#ormandam\u00fclakatiptal": {
    "duration": 15,
    "tweet_volume": -1
  },
  "#MilanTorino": {
    "duration": 240,
    "tweet_volume": 11193
  },
  "#\u0627\u062f\u0639\u0645_\u0645\u0628\u0627\u062f\u0631\u0647_\u062c\u0645\u0647\u0648\u0631_\u0627\u0644\u0627\u0647\u0644\u064a": {
    "duration": 45,
    "tweet_volume": 84150
  },
  "Jujuy": {
    "duration": 210,
    "tweet_volume": 22361
  },
  "Raiola": {
    "duration": 15,
    "tweet_volume": -1
  },
  "#COAC2020S2": {
    "duration": 240,
    "tweet_volume": 10746
  },
  "#ObamaWasBetterAtEverything": {
    "duration": 240,
    "tweet_volume": 36294
  },
  "#GGMU": {
    "duration": 30,
    "tweet_volume": -1
  },
  "#\u0627\u0644\u062f\u0646\u064a\u0627_\u0639\u0644\u0645\u062a\u0646\u064a": {
    "duration": 240,
    "tweet_volume": 20446
  },
  "Reece James": {
    "duration": 30,
    "tweet_volume": -1
  },
  "#EastEnders35": {
    "duration": 165,
    "tweet_volume": -1
  },
  "#SevsenKe\u015fke": {
    "duration": 30,
    "tweet_volume": 16847
  },
  "#\u0648\u064a\u0646_\u0627\u0644\u0645\u064a\u0647_\u0627\u0644\u0641_\u064a\u0627\u062e\u0627\u0644\u062f": {
    "duration": 120,
    "tweet_volume": -1
  },
  "Maguire": {
    "duration": 210,
    "tweet_volume": 88335
  },
  "Giroud": {
    "duration": 195,
    "tweet_volume": 35923
  },
  "Michy": {
    "duration": 90,
    "tweet_volume": 16304
  },
  "#Fatima": {
    "duration": 15,
    "tweet_volume": 62249
  },
  "#c4debate": {
    "duration": 90,
    "tweet_volume": -1
  },
  "#MariesAuPremierRegard": {
    "duration": 210,
    "tweet_volume": -1
  },
  "Martial": {
    "duration": 195,
    "tweet_volume": 75650
  },
  "Wan Bissaka": {
    "duration": 150,
    "tweet_volume": -1
  },
  "Ighalo": {
    "duration": 150,
    "tweet_volume": 75410
  },
  "Anthony Taylor": {
    "duration": 105,
    "tweet_volume": -1
  },
  "Daniel James": {
    "duration": 105,
    "tweet_volume": -1
  },
  "Luke Shaw": {
    "duration": 30,
    "tweet_volume": -1
  },
  "Caballero": {
    "duration": 90,
    "tweet_volume": 17119
  },
  "Christensen": {
    "duration": 120,
    "tweet_volume": -1
  },
  "#UniversityChallenge": {
    "duration": 60,
    "tweet_volume": -1
  },
  "#seniny\u00fcz\u00fcnden": {
    "duration": 15,
    "tweet_volume": -1
  },
  "Willian": {
    "duration": 180,
    "tweet_volume": 20412
  },
  "Lampard": {
    "duration": 90,
    "tweet_volume": 35243
  },
  "#MeteteTuRifaEnElCulo": {
    "duration": 105,
    "tweet_volume": -1
  },
  "#Pit4Busch": {
    "duration": 135,
    "tweet_volume": 89899
  },
  "Azpi": {
    "duration": 165,
    "tweet_volume": -1
  },
  "Zouma": {
    "duration": 60,
    "tweet_volume": 11763
  },
  "#LAmicaGeniale": {
    "duration": 165,
    "tweet_volume": 22055
  },
  "Chelsea": {
    "duration": 90,
    "tweet_volume": 309745
  },
  "Bruno Fernandes": {
    "duration": 75,
    "tweet_volume": 27902
  },
  "VARchester United": {
    "duration": 60,
    "tweet_volume": -1
  },
  "Kepa": {
    "duration": 90,
    "tweet_volume": -1
  },
  "Kovacic": {
    "duration": 45,
    "tweet_volume": -1
  },
  "Stamford Bridge": {
    "duration": 150,
    "tweet_volume": 23051
  },
  "#\u062a\u0634\u064a\u0644\u0633\u064a_\u0645\u0627\u0646\u0634\u0633\u062a\u0631_\u064a\u0648\u0646\u0627\u064a\u062a\u062f": {
    "duration": 135,
    "tweet_volume": 10846
  },
  "#gfvip2020": {
    "duration": 150,
    "tweet_volume": -1
  },
  "#LBCRCL": {
    "duration": 30,
    "tweet_volume": -1
  },
  "Stenhouse": {
    "duration": 135,
    "tweet_volume": -1
  },
  "Gary Neville": {
    "duration": 75,
    "tweet_volume": -1
  },
  "#ManUtd": {
    "duration": 45,
    "tweet_volume": -1
  },
  "#ColdFeet": {
    "duration": 90,
    "tweet_volume": -1
  },
  "Man U": {
    "duration": 45,
    "tweet_volume": 15151
  },
  "christensen": {
    "duration": 15,
    "tweet_volume": -1
  },
  "#PresidentWarren": {
    "duration": 105,
    "tweet_volume": 34759
  },
  "#LoveFromSean": {
    "duration": 105,
    "tweet_volume": 65642
  },
  "Burak \u00d6\u011fretmen": {
    "duration": 90,
    "tweet_volume": -1
  },
  "#MUNCHE": {
    "duration": 15,
    "tweet_volume": -1
  },
  "Kante": {
    "duration": 60,
    "tweet_volume": 18710
  },
  "#MaestrosDeLaCostura": {
    "duration": 75,
    "tweet_volume": -1
  },
  "#\u9154\u3063\u305f\u52e2\u3044\u3067\u3057\u3067\u304b\u3057\u305f\u3053\u3068": {
    "duration": 75,
    "tweet_volume": -1
  },
  "zouma": {
    "duration": 15,
    "tweet_volume": 12110
  },
  "#PitForBusch": {
    "duration": 30,
    "tweet_volume": 11388
  },
  "#confesiondeaida": {
    "duration": 15,
    "tweet_volume": 39553
  },
  "#conquis5": {
    "duration": 45,
    "tweet_volume": -1
  },
  "F\u00e1tima": {
    "duration": 30,
    "tweet_volume": 333700
  },
  "Lila": {
    "duration": 30,
    "tweet_volume": 18780
  },
  "#\u4e0b\u30cd\u30bf\u306b\u805e\u3053\u3048\u306a\u304f\u3082\u306a\u3044\u8a00\u8449": {
    "duration": 45,
    "tweet_volume": -1
  },
  "#DiaMundialDoGato": {
    "duration": 45,
    "tweet_volume": -1
  },
  "#Sweepstakes": {
    "duration": 30,
    "tweet_volume": 121517
  },
  "Harvick": {
    "duration": 30,
    "tweet_volume": -1
  },
  "Botta": {
    "duration": 30,
    "tweet_volume": -1
  },
  "kante": {
    "duration": 15,
    "tweet_volume": 18314
  },
  "#\u0648\u0634_\u0645\u0633\u0647\u0631\u0643_\u0627\u0644\u0627\u0646": {
    "duration": 30,
    "tweet_volume": -1
  },
  "#milantorino": {
    "duration": 15,
    "tweet_volume": 11091
  },
  "#randomactsofcolourpop": {
    "duration": 15,
    "tweet_volume": -1
  },
  "#cblive": {
    "duration": 30,
    "tweet_volume": -1
  },
  "#\u611b\u77e5\u770c\u99c5\u540d\u5730\u540d\u30af\u30a4\u30ba": {
    "duration": 30,
    "tweet_volume": -1
  },
  "Logano": {
    "duration": 15,
    "tweet_volume": -1
  },
  "michy": {
    "duration": 15,
    "tweet_volume": 16518
  },
  "\u5fa1\u5802\u7b4b\u7dda": {
    "duration": 15,
    "tweet_volume": -1
  },
  "#PresidenciaComprada": {
    "duration": 15,
    "tweet_volume": -1
  }
}